lucidmotors/__init__.py
lucidmotors/common.py
lucidmotors/const.py
lucidmotors/exceptions.py
lucidmotors/gen/__init__.py
lucidmotors/gen/charging_service_pb2.py
lucidmotors/gen/charging_service_pb2.py.orig
lucidmotors/gen/charging_service_pb2.pyi
lucidmotors/gen/charging_service_pb2.pyi.orig
lucidmotors/gen/charging_service_pb2_grpc.py
lucidmotors/gen/charging_service_pb2_grpc.py.orig
lucidmotors/gen/keyfob_service_pb2.py
lucidmotors/gen/keyfob_service_pb2.py.orig
lucidmotors/gen/keyfob_service_pb2.pyi
lucidmotors/gen/keyfob_service_pb2.pyi.orig
lucidmotors/gen/keyfob_service_pb2_grpc.py
lucidmotors/gen/keyfob_service_pb2_grpc.py.orig
lucidmotors/gen/login_session_pb2.py
lucidmotors/gen/login_session_pb2.py.orig
lucidmotors/gen/login_session_pb2.pyi
lucidmotors/gen/login_session_pb2.pyi.orig
lucidmotors/gen/login_session_pb2_grpc.py
lucidmotors/gen/login_session_pb2_grpc.py.orig
lucidmotors/gen/salesforce_service_pb2.py
lucidmotors/gen/salesforce_service_pb2.py.orig
lucidmotors/gen/salesforce_service_pb2.pyi
lucidmotors/gen/salesforce_service_pb2.pyi.orig
lucidmotors/gen/salesforce_service_pb2_grpc.py
lucidmotors/gen/salesforce_service_pb2_grpc.py.orig
lucidmotors/gen/sentry_service_pb2.py
lucidmotors/gen/sentry_service_pb2.py.orig
lucidmotors/gen/sentry_service_pb2.pyi
lucidmotors/gen/sentry_service_pb2.pyi.orig
lucidmotors/gen/sentry_service_pb2_grpc.py
lucidmotors/gen/sentry_service_pb2_grpc.py.orig
lucidmotors/gen/subscription_service_pb2.py
lucidmotors/gen/subscription_service_pb2.py.orig
lucidmotors/gen/subscription_service_pb2.pyi
lucidmotors/gen/subscription_service_pb2.pyi.orig
lucidmotors/gen/subscription_service_pb2_grpc.py
lucidmotors/gen/subscription_service_pb2_grpc.py.orig
lucidmotors/gen/trip_service_pb2.py
lucidmotors/gen/trip_service_pb2.py.orig
lucidmotors/gen/trip_service_pb2.pyi
lucidmotors/gen/trip_service_pb2.pyi.orig
lucidmotors/gen/trip_service_pb2_grpc.py
lucidmotors/gen/trip_service_pb2_grpc.py.orig
lucidmotors-1.4.1.dist-info/LICENSE
lucidmotors-1.4.1.dist-info/METADATA
lucidmotors-1.4.1.dist-info/WHEEL
lucidmotors-1.4.1.dist-info/RECORD
