Metadata-Version: 2.1
Name: lucidmotors
Version: 1.4.1
Summary: 
Author: Nick Shipp
Author-email: git@segbrk.com
Requires-Python: >=3.12,<4.0
Classifier: Programming Language :: Python :: 3
Classifier: Programming Language :: Python :: 3.12
Classifier: Programming Language :: Python :: 3.13
Requires-Dist: grpc-stubs (>=1.53.0,<2.0.0)
Requires-Dist: grpcio (>=1.75.1,<2.0.0)
Requires-Dist: protobuf (>=6.31.1,<7.0.0)
